{"nodes": [{"id": "bookit_src_lib_actions_createbooking_ts", "label": "createBooking.ts", "file_type": "code", "source_file": "bookit\\src\\lib\\actions\\createBooking.ts", "source_location": "L1"}, {"id": "createbooking_createbooking", "label": "createBooking()", "file_type": "code", "source_file": "bookit\\src\\lib\\actions\\createBooking.ts", "source_location": "L80"}], "edges": [{"source": "bookit_src_lib_actions_createbooking_ts", "target": "zod", "relation": "imports_from", "confidence": "EXTRACTED", "source_file": "bookit\\src\\lib\\actions\\createBooking.ts", "source_location": "L3", "weight": 1.0}, {"source": "bookit_src_lib_actions_createbooking_ts", "target": "server", "relation": "imports_from", "confidence": "EXTRACTED", "source_file": "bookit\\src\\lib\\actions\\createBooking.ts", "source_location": "L4", "weight": 1.0}, {"source": "bookit_src_lib_actions_createbooking_ts", "target": "admin", "relation": "imports_from", "confidence": "EXTRACTED", "source_file": "bookit\\src\\lib\\actions\\createBooking.ts", "source_location": "L5", "weight": 1.0}, {"source": "bookit_src_lib_actions_createbooking_ts", "target": "dynamicpricing", "relation": "imports_from", "confidence": "EXTRACTED", "source_file": "bookit\\src\\lib\\actions\\createBooking.ts", "source_location": "L6", "weight": 1.0}, {"source": "bookit_src_lib_actions_createbooking_ts", "target": "bookingengine", "relation": "imports_from", "confidence": "EXTRACTED", "source_file": "bookit\\src\\lib\\actions\\createBooking.ts", "source_location": "L7", "weight": 1.0}, {"source": "bookit_src_lib_actions_createbooking_ts", "target": "telegram", "relation": "imports_from", "confidence": "EXTRACTED", "source_file": "bookit\\src\\lib\\actions\\createBooking.ts", "source_location": "L8", "weight": 1.0}, {"source": "bookit_src_lib_actions_createbooking_ts", "target": "cache", "relation": "imports_from", "confidence": "EXTRACTED", "source_file": "bookit\\src\\lib\\actions\\createBooking.ts", "source_location": "L9", "weight": 1.0}, {"source": "bookit_src_lib_actions_createbooking_ts", "target": "booking", "relation": "imports_from", "confidence": "EXTRACTED", "source_file": "bookit\\src\\lib\\actions\\createBooking.ts", "source_location": "L10", "weight": 1.0}, {"source": "bookit_src_lib_actions_createbooking_ts", "target": "createbooking_createbooking", "relation": "contains", "confidence": "EXTRACTED", "source_file": "bookit\\src\\lib\\actions\\createBooking.ts", "source_location": "L80", "weight": 1.0}]}