{"nodes": [{"id": "bookit_src_components_master_marketing_broadcasteditor_tsx", "label": "BroadcastEditor.tsx", "file_type": "code", "source_file": "bookit\\src\\components\\master\\marketing\\BroadcastEditor.tsx", "source_location": "L1"}, {"id": "broadcasteditor_handlesearchinput", "label": "handleSearchInput()", "file_type": "code", "source_file": "bookit\\src\\components\\master\\marketing\\BroadcastEditor.tsx", "source_location": "L134"}, {"id": "broadcasteditor_toggletag", "label": "toggleTag()", "file_type": "code", "source_file": "bookit\\src\\components\\master\\marketing\\BroadcastEditor.tsx", "source_location": "L143"}, {"id": "broadcasteditor_togglechannel", "label": "toggleChannel()", "file_type": "code", "source_file": "bookit\\src\\components\\master\\marketing\\BroadcastEditor.tsx", "source_location": "L146"}, {"id": "broadcasteditor_toggleexclude", "label": "toggleExclude()", "file_type": "code", "source_file": "bookit\\src\\components\\master\\marketing\\BroadcastEditor.tsx", "source_location": "L149"}, {"id": "broadcasteditor_toggleselect", "label": "toggleSelect()", "file_type": "code", "source_file": "bookit\\src\\components\\master\\marketing\\BroadcastEditor.tsx", "source_location": "L156"}], "edges": [{"source": "bookit_src_components_master_marketing_broadcasteditor_tsx", "target": "react", "relation": "imports_from", "confidence": "EXTRACTED", "source_file": "bookit\\src\\components\\master\\marketing\\BroadcastEditor.tsx", "source_location": "L3", "weight": 1.0}, {"source": "bookit_src_components_master_marketing_broadcasteditor_tsx", "target": "framer_motion", "relation": "imports_from", "confidence": "EXTRACTED", "source_file": "bookit\\src\\components\\master\\marketing\\BroadcastEditor.tsx", "source_location": "L4", "weight": 1.0}, {"source": "bookit_src_components_master_marketing_broadcasteditor_tsx", "target": "lucide_react", "relation": "imports_from", "confidence": "EXTRACTED", "source_file": "bookit\\src\\components\\master\\marketing\\BroadcastEditor.tsx", "source_location": "L5", "weight": 1.0}, {"source": "bookit_src_components_master_marketing_broadcasteditor_tsx", "target": "usebroadcasts", "relation": "imports_from", "confidence": "EXTRACTED", "source_file": "bookit\\src\\components\\master\\marketing\\BroadcastEditor.tsx", "source_location": "L10", "weight": 1.0}, {"source": "bookit_src_components_master_marketing_broadcasteditor_tsx", "target": "useservices", "relation": "imports_from", "confidence": "EXTRACTED", "source_file": "bookit\\src\\components\\master\\marketing\\BroadcastEditor.tsx", "source_location": "L15", "weight": 1.0}, {"source": "bookit_src_components_master_marketing_broadcasteditor_tsx", "target": "database", "relation": "imports_from", "confidence": "EXTRACTED", "source_file": "bookit\\src\\components\\master\\marketing\\BroadcastEditor.tsx", "source_location": "L16", "weight": 1.0}, {"source": "bookit_src_components_master_marketing_broadcasteditor_tsx", "target": "actions", "relation": "imports_from", "confidence": "EXTRACTED", "source_file": "bookit\\src\\components\\master\\marketing\\BroadcastEditor.tsx", "source_location": "L17", "weight": 1.0}, {"source": "bookit_src_components_master_marketing_broadcasteditor_tsx", "target": "actions", "relation": "imports_from", "confidence": "EXTRACTED", "source_file": "bookit\\src\\components\\master\\marketing\\BroadcastEditor.tsx", "source_location": "L18", "weight": 1.0}, {"source": "bookit_src_components_master_marketing_broadcasteditor_tsx", "target": "pluraluk", "relation": "imports_from", "confidence": "EXTRACTED", "source_file": "bookit\\src\\components\\master\\marketing\\BroadcastEditor.tsx", "source_location": "L19", "weight": 1.0}, {"source": "bookit_src_components_master_marketing_broadcasteditor_tsx", "target": "broadcasteditor_handlesearchinput", "relation": "contains", "confidence": "EXTRACTED", "source_file": "bookit\\src\\components\\master\\marketing\\BroadcastEditor.tsx", "source_location": "L134", "weight": 1.0}, {"source": "bookit_src_components_master_marketing_broadcasteditor_tsx", "target": "broadcasteditor_toggletag", "relation": "contains", "confidence": "EXTRACTED", "source_file": "bookit\\src\\components\\master\\marketing\\BroadcastEditor.tsx", "source_location": "L143", "weight": 1.0}, {"source": "bookit_src_components_master_marketing_broadcasteditor_tsx", "target": "broadcasteditor_togglechannel", "relation": "contains", "confidence": "EXTRACTED", "source_file": "bookit\\src\\components\\master\\marketing\\BroadcastEditor.tsx", "source_location": "L146", "weight": 1.0}, {"source": "bookit_src_components_master_marketing_broadcasteditor_tsx", "target": "broadcasteditor_toggleexclude", "relation": "contains", "confidence": "EXTRACTED", "source_file": "bookit\\src\\components\\master\\marketing\\BroadcastEditor.tsx", "source_location": "L149", "weight": 1.0}, {"source": "bookit_src_components_master_marketing_broadcasteditor_tsx", "target": "broadcasteditor_toggleselect", "relation": "contains", "confidence": "EXTRACTED", "source_file": "bookit\\src\\components\\master\\marketing\\BroadcastEditor.tsx", "source_location": "L156", "weight": 1.0}]}