{"nodes": [{"id": "bookit_src_components_ui_bentocard_tsx", "label": "BentoCard.tsx", "file_type": "code", "source_file": "bookit\\src\\components\\ui\\BentoCard.tsx", "source_location": "L1"}, {"id": "bentocard_bentocard", "label": "BentoCard()", "file_type": "code", "source_file": "bookit\\src\\components\\ui\\BentoCard.tsx", "source_location": "L27"}, {"id": "bentocard_cn", "label": "cn()", "file_type": "code", "source_file": "bookit\\src\\components\\ui\\BentoCard.tsx", "source_location": "L43"}], "edges": [{"source": "bookit_src_components_ui_bentocard_tsx", "target": "react", "relation": "imports_from", "confidence": "EXTRACTED", "source_file": "bookit\\src\\components\\ui\\BentoCard.tsx", "source_location": "L3", "weight": 1.0}, {"source": "bookit_src_components_ui_bentocard_tsx", "target": "framer_motion", "relation": "imports_from", "confidence": "EXTRACTED", "source_file": "bookit\\src\\components\\ui\\BentoCard.tsx", "source_location": "L4", "weight": 1.0}, {"source": "bookit_src_components_ui_bentocard_tsx", "target": "lucide_react", "relation": "imports_from", "confidence": "EXTRACTED", "source_file": "bookit\\src\\components\\ui\\BentoCard.tsx", "source_location": "L5", "weight": 1.0}, {"source": "bookit_src_components_ui_bentocard_tsx", "target": "cn", "relation": "imports_from", "confidence": "EXTRACTED", "source_file": "bookit\\src\\components\\ui\\BentoCard.tsx", "source_location": "L6", "weight": 1.0}, {"source": "bookit_src_components_ui_bentocard_tsx", "target": "bentocard_bentocard", "relation": "contains", "confidence": "EXTRACTED", "source_file": "bookit\\src\\components\\ui\\BentoCard.tsx", "source_location": "L27", "weight": 1.0}, {"source": "bookit_src_components_ui_bentocard_tsx", "target": "bentocard_cn", "relation": "contains", "confidence": "EXTRACTED", "source_file": "bookit\\src\\components\\ui\\BentoCard.tsx", "source_location": "L43", "weight": 1.0}]}