{"nodes": [{"id": "monobank_acquiring_monobank_acquiring_examples_php_server_php", "label": "server.php", "file_type": "code", "source_file": "monobank-acquiring\\monobank-acquiring\\examples\\php\\server.php", "source_location": "L1"}, {"id": "server_mono_request", "label": "mono_request()", "file_type": "code", "source_file": "monobank-acquiring\\monobank-acquiring\\examples\\php\\server.php", "source_location": "L37"}, {"id": "server_get_pubkey_pem", "label": "get_pubkey_pem()", "file_type": "code", "source_file": "monobank-acquiring\\monobank-acquiring\\examples\\php\\server.php", "source_location": "L69"}, {"id": "server_reset_pubkey", "label": "reset_pubkey()", "file_type": "code", "source_file": "monobank-acquiring\\monobank-acquiring\\examples\\php\\server.php", "source_location": "L78"}, {"id": "server_verify_signature", "label": "verify_signature()", "file_type": "code", "source_file": "monobank-acquiring\\monobank-acquiring\\examples\\php\\server.php", "source_location": "L82"}, {"id": "server_json_response", "label": "json_response()", "file_type": "code", "source_file": "monobank-acquiring\\monobank-acquiring\\examples\\php\\server.php", "source_location": "L96"}], "edges": [{"source": "monobank_acquiring_monobank_acquiring_examples_php_server_php", "target": "server_mono_request", "relation": "contains", "confidence": "EXTRACTED", "source_file": "monobank-acquiring\\monobank-acquiring\\examples\\php\\server.php", "source_location": "L37", "weight": 1.0}, {"source": "monobank_acquiring_monobank_acquiring_examples_php_server_php", "target": "server_get_pubkey_pem", "relation": "contains", "confidence": "EXTRACTED", "source_file": "monobank-acquiring\\monobank-acquiring\\examples\\php\\server.php", "source_location": "L69", "weight": 1.0}, {"source": "monobank_acquiring_monobank_acquiring_examples_php_server_php", "target": "server_reset_pubkey", "relation": "contains", "confidence": "EXTRACTED", "source_file": "monobank-acquiring\\monobank-acquiring\\examples\\php\\server.php", "source_location": "L78", "weight": 1.0}, {"source": "monobank_acquiring_monobank_acquiring_examples_php_server_php", "target": "server_verify_signature", "relation": "contains", "confidence": "EXTRACTED", "source_file": "monobank-acquiring\\monobank-acquiring\\examples\\php\\server.php", "source_location": "L82", "weight": 1.0}, {"source": "monobank_acquiring_monobank_acquiring_examples_php_server_php", "target": "server_json_response", "relation": "contains", "confidence": "EXTRACTED", "source_file": "monobank-acquiring\\monobank-acquiring\\examples\\php\\server.php", "source_location": "L96", "weight": 1.0}, {"source": "server_get_pubkey_pem", "target": "server_mono_request", "relation": "calls", "confidence": "EXTRACTED", "source_file": "monobank-acquiring\\monobank-acquiring\\examples\\php\\server.php", "source_location": "L71", "weight": 1.0}, {"source": "server_verify_signature", "target": "server_get_pubkey_pem", "relation": "calls", "confidence": "EXTRACTED", "source_file": "monobank-acquiring\\monobank-acquiring\\examples\\php\\server.php", "source_location": "L83", "weight": 1.0}]}