{"nodes": [{"id": "monobank_acquiring_monobank_acquiring_examples_nodejs_server_js", "label": "server.js", "file_type": "code", "source_file": "monobank-acquiring\\monobank-acquiring\\examples\\nodejs\\server.js", "source_location": "L1"}, {"id": "server_monorequest", "label": "monoRequest()", "file_type": "code", "source_file": "monobank-acquiring\\monobank-acquiring\\examples\\nodejs\\server.js", "source_location": "L45"}, {"id": "server_getpubkey", "label": "getPubKey()", "file_type": "code", "source_file": "monobank-acquiring\\monobank-acquiring\\examples\\nodejs\\server.js", "source_location": "L68"}, {"id": "server_resetpubkey", "label": "resetPubKey()", "file_type": "code", "source_file": "monobank-acquiring\\monobank-acquiring\\examples\\nodejs\\server.js", "source_location": "L76"}, {"id": "server_verifysignature", "label": "verifySignature()", "file_type": "code", "source_file": "monobank-acquiring\\monobank-acquiring\\examples\\nodejs\\server.js", "source_location": "L80"}], "edges": [{"source": "monobank_acquiring_monobank_acquiring_examples_nodejs_server_js", "target": "server_monorequest", "relation": "contains", "confidence": "EXTRACTED", "source_file": "monobank-acquiring\\monobank-acquiring\\examples\\nodejs\\server.js", "source_location": "L45", "weight": 1.0}, {"source": "monobank_acquiring_monobank_acquiring_examples_nodejs_server_js", "target": "server_getpubkey", "relation": "contains", "confidence": "EXTRACTED", "source_file": "monobank-acquiring\\monobank-acquiring\\examples\\nodejs\\server.js", "source_location": "L68", "weight": 1.0}, {"source": "monobank_acquiring_monobank_acquiring_examples_nodejs_server_js", "target": "server_resetpubkey", "relation": "contains", "confidence": "EXTRACTED", "source_file": "monobank-acquiring\\monobank-acquiring\\examples\\nodejs\\server.js", "source_location": "L76", "weight": 1.0}, {"source": "monobank_acquiring_monobank_acquiring_examples_nodejs_server_js", "target": "server_verifysignature", "relation": "contains", "confidence": "EXTRACTED", "source_file": "monobank-acquiring\\monobank-acquiring\\examples\\nodejs\\server.js", "source_location": "L80", "weight": 1.0}, {"source": "server_getpubkey", "target": "server_monorequest", "relation": "calls", "confidence": "EXTRACTED", "source_file": "monobank-acquiring\\monobank-acquiring\\examples\\nodejs\\server.js", "source_location": "L70", "weight": 1.0}, {"source": "server_verifysignature", "target": "server_getpubkey", "relation": "calls", "confidence": "EXTRACTED", "source_file": "monobank-acquiring\\monobank-acquiring\\examples\\nodejs\\server.js", "source_location": "L81", "weight": 1.0}]}